morgan/__init__.py
morgan/connection.py
morgan/exceptions.py
morgan/orm.py
py_morgan_orm-0.2.0.dist-info/LICENSE
py_morgan_orm-0.2.0.dist-info/METADATA
py_morgan_orm-0.2.0.dist-info/WHEEL
py_morgan_orm-0.2.0.dist-info/top_level.txt
py_morgan_orm-0.2.0.dist-info/RECORD
