Metadata-Version: 2.1
Name: py-morgan-orm
Version: 0.2.0
Summary: A simple and easy-to-use ORM for managing your database queries.
Author-email: Vicente Gutiérrez <gtz.rvera@gmail.com>
Project-URL: Homepage, https://github.com/vcgtz/py-morgan-orm
Project-URL: Issues, https://github.com/vcgtz/py-morgan-orm/issues
Classifier: Programming Language :: Python :: 3
Classifier: License :: OSI Approved :: MIT License
Classifier: Operating System :: OS Independent
Requires-Python: >=3.9
License-File: LICENSE
